beep/__init__.py
beep/cmd.py
beep/model.py
beep/conversion_schemas/FastCharge_conversion.yaml
beep/conversion_schemas/README.md
beep/conversion_schemas/__init__.py
beep/conversion_schemas/arbin_conversion.yaml
beep/conversion_schemas/biologic_conversion.yaml
beep/conversion_schemas/indigo_conversion.yaml
beep/conversion_schemas/maccor_conversion.yaml
beep/conversion_schemas/maccor_waveform_conversion.yaml
beep/conversion_schemas/neware_conversion.yaml
beep/conversion_schemas/novonix_conversion.yaml
beep/conversion_schemas/structured_dtypes.yaml
beep/conversion_schemas/xTESLADIAG_conversion.yaml
beep/deprecated/parameters_lookup.py
beep/deprecated/models/custom_model.model
beep/deprecated/models/d3batt_multi_point.model
beep/deprecated/models/d3batt_single_point.model
beep/deprecated/protocol_parameters/Drive_parameters - GP.csv
beep/deprecated/protocol_parameters/Form_parameters - GP.csv
beep/deprecated/protocol_parameters/Iris_parameters - GP.csv
beep/deprecated/protocol_parameters/PreDiag_parameters - GP.csv
beep/deprecated/protocol_parameters/PredictionDiagnostics_parameters - GP.csv
beep/deprecated/protocol_parameters/RapidC_parameters - GP.csv
beep/deprecated/protocol_parameters/Talos_parameters - GP.csv
beep/deprecated/protocol_parameters/intracell_info/anode_test.csv
beep/deprecated/protocol_parameters/intracell_info/cathode_test.csv
beep/features/__init__.py
beep/features/base.py
beep/features/core.py
beep/features/featurizer_helpers.py
beep/features/intracell_analysis.py
beep/features/intracell_analysis_v2.py
beep/features/intracell_losses.py
beep/features/intracell_losses_v2.py
beep/features/principal_components.py
beep/features/tests/__init__.py
beep/features/tests/test_base.py
beep/features/tests/test_features.py
beep/features/tests/test_intracell_analysis.py
beep/features/tests/test_intracell_analysis_v2.py
beep/features/tests/test_principal_components.py
beep/prediction/__init__.py
beep/prediction/beep_data_splitter.py
beep-2025.1.29.19.dist-info/LICENSE
beep-2025.1.29.19.dist-info/METADATA
beep-2025.1.29.19.dist-info/WHEEL
beep-2025.1.29.19.dist-info/entry_points.txt
beep-2025.1.29.19.dist-info/top_level.txt
beep-2025.1.29.19.dist-info/RECORD
