Metadata-Version: 2.2
Name: beep
Version: 2025.1.29.19
Summary: beep is a python package supporting Battery Estimation and Early Prediction of battery cycle life.
Home-page: https://github.com/TRI-AMDD/beep
Author: Energy and Materials - Toyota Research Institute
Maintainer: Energy and Materials - Toyota Research Institute
License: Apache
Keywords: materials,battery,chemistry,science,electrochemistry,energy,AI,artificial intelligence
Classifier: Programming Language :: Python :: 3
Classifier: License :: OSI Approved :: Apache Software License
Classifier: Operating System :: OS Independent
License-File: LICENSE
Requires-Dist: numpy==1.24.4
Requires-Dist: monty[yaml]==2023.9.25
Requires-Dist: scipy==1.11.1
Requires-Dist: scikit-learn==1.3.2
Requires-Dist: pandas==2.0.3
Requires-Dist: tqdm==4.66.5
Requires-Dist: boto3==1.34.157
Requires-Dist: botocore==1.34.157
Requires-Dist: pytz==2024.1
Requires-Dist: watchtower==3.2.0
Requires-Dist: msgpack-python==0.5.6
Requires-Dist: python-dateutil==2.9.0.post0
Requires-Dist: ruamel.yaml==0.18.6
Requires-Dist: xmltodict==0.13.0
Requires-Dist: pydash==8.0.3
Requires-Dist: lmfit==1.3.2
Requires-Dist: click==8.1.7
Requires-Dist: matplotlib==3.7.5
Requires-Dist: h5py==3.11.0
Provides-Extra: tests
Requires-Dist: pytest-cov==5.0.0; extra == "tests"
Requires-Dist: coveralls==4.0.1; extra == "tests"
Requires-Dist: memory_profiler==0.61.0; extra == "tests"
Requires-Dist: requests; extra == "tests"
Dynamic: author
Dynamic: classifier
Dynamic: description
Dynamic: description-content-type
Dynamic: home-page
Dynamic: keywords
Dynamic: license
Dynamic: maintainer
Dynamic: provides-extra
Dynamic: requires-dist
Dynamic: summary
